thirdparty/__init__.py
thirdparty/builder/__init__.py
thirdparty/builder/assist/__init__.py
thirdparty/builder/assist/cli.py
thirdparty_builder_assist-0.1.1.dist-info/LICENSE
thirdparty_builder_assist-0.1.1.dist-info/METADATA
thirdparty_builder_assist-0.1.1.dist-info/WHEEL
thirdparty_builder_assist-0.1.1.dist-info/entry_points.txt
thirdparty_builder_assist-0.1.1.dist-info/top_level.txt
thirdparty_builder_assist-0.1.1.dist-info/RECORD
