Metadata-Version: 2.1
Name: thirdparty-builder-assist
Version: 0.1.1
Summary: Tool for automatically building source on save.
Home-page: https://github.com/third-party-dev/builder.assist
Author: Vincent Agriesti
Author-email: crazychenz@gmail.com
License: UNKNOWN
Platform: UNKNOWN
Classifier: Programming Language :: Python :: 3
Classifier: License :: OSI Approved :: MIT License
Classifier: Environment :: Console
Classifier: Intended Audience :: Developers
Classifier: Operating System :: POSIX :: Linux
Classifier: Topic :: Software Development :: Build Tools
Classifier: Topic :: Utilities
Requires-Python: ~=3.7
Requires-Dist: inotify
